<?xml version="1.0" encoding="UTF-8"?>
<objects serializationModel="Studio.01.10.00">
    <object class="Event" id="{0b78744e-853f-41c0-81da-8956bb7ee45f}">
        <property name="name">
            <value>Turbine Cleanup</value>
        </property>
        <property name="outputFormat">
            <value>1</value>
        </property>
        <relationship name="folder">
            <destination>{8b029fe0-3d3c-4333-b26c-7691441006db}</destination>
        </relationship>
        <relationship name="mixer">
            <destination>{955e1f67-0b3c-4f95-b7ef-a52920b3e68c}</destination>
        </relationship>
        <relationship name="masterTrack">
            <destination>{6d3dfc13-7550-43c2-a87a-040a2a4a97f7}</destination>
        </relationship>
        <relationship name="mixerInput">
            <destination>{42d2bcc7-0279-4f5d-bb18-785b260faa02}</destination>
        </relationship>
        <relationship name="automatableProperties">
            <destination>{87fcdcfa-700e-453e-a129-311389490800}</destination>
        </relationship>
        <relationship name="markerTracks">
            <destination>{c67075e1-006f-48b2-b2c8-082a7f37710c}</destination>
        </relationship>
        <relationship name="groupTracks">
            <destination>{ed58b2e4-57e2-46dd-b8b3-e20bc3da1502}</destination>
        </relationship>
        <relationship name="timeline">
            <destination>{e54c6805-a726-49f9-bb64-06f6ae63d48d}</destination>
        </relationship>
    </object>
    <object class="EventMixer" id="{955e1f67-0b3c-4f95-b7ef-a52920b3e68c}">
        <relationship name="masterBus">
            <destination>{8af57796-ecf0-4baa-adfd-03bc64187455}</destination>
        </relationship>
    </object>
    <object class="MasterTrack" id="{6d3dfc13-7550-43c2-a87a-040a2a4a97f7}">
        <relationship name="mixerGroup">
            <destination>{8af57796-ecf0-4baa-adfd-03bc64187455}</destination>
        </relationship>
    </object>
    <object class="MixerInput" id="{42d2bcc7-0279-4f5d-bb18-785b260faa02}">
        <relationship name="effectChain">
            <destination>{782c4012-2f4a-49c8-ad29-0ee26757ddfd}</destination>
        </relationship>
        <relationship name="panner">
            <destination>{e61637a4-3b2a-46f8-ae4f-a5fc93f83e89}</destination>
        </relationship>
        <relationship name="output">
            <destination>{8558a266-2c05-4155-8d6b-2af335260b96}</destination>
        </relationship>
    </object>
    <object class="EventAutomatableProperties" id="{87fcdcfa-700e-453e-a129-311389490800}"/>
    <object class="MarkerTrack" id="{c67075e1-006f-48b2-b2c8-082a7f37710c}"/>
    <object class="GroupTrack" id="{ed58b2e4-57e2-46dd-b8b3-e20bc3da1502}">
        <relationship name="mixerGroup">
            <destination>{16485980-fc88-4037-979a-8e68ab7e77b9}</destination>
        </relationship>
    </object>
    <object class="Timeline" id="{e54c6805-a726-49f9-bb64-06f6ae63d48d}"/>
    <object class="EventMixerMaster" id="{8af57796-ecf0-4baa-adfd-03bc64187455}">
        <relationship name="effectChain">
            <destination>{e44c2840-6c61-4428-854d-1a899a20e4d4}</destination>
        </relationship>
        <relationship name="panner">
            <destination>{48c867fd-18b7-4010-9eff-deca9cc48a3c}</destination>
        </relationship>
        <relationship name="mixer">
            <destination>{955e1f67-0b3c-4f95-b7ef-a52920b3e68c}</destination>
        </relationship>
    </object>
    <object class="MixerBusEffectChain" id="{782c4012-2f4a-49c8-ad29-0ee26757ddfd}">
        <relationship name="effects">
            <destination>{eeeaf0d2-04a5-46dd-b975-2ad823a516f5}</destination>
        </relationship>
    </object>
    <object class="MixerBusPanner" id="{e61637a4-3b2a-46f8-ae4f-a5fc93f83e89}"/>
    <object class="EventMixerGroup" id="{16485980-fc88-4037-979a-8e68ab7e77b9}">
        <property name="name">
            <value>Audio 1</value>
        </property>
        <relationship name="effectChain">
            <destination>{7c7c79ce-363f-4f6d-8849-a1a4d633887e}</destination>
        </relationship>
        <relationship name="panner">
            <destination>{729f48dc-30f8-4de9-b212-e4da367e2b7e}</destination>
        </relationship>
        <relationship name="output">
            <destination>{8af57796-ecf0-4baa-adfd-03bc64187455}</destination>
        </relationship>
    </object>
    <object class="MixerBusEffectChain" id="{e44c2840-6c61-4428-854d-1a899a20e4d4}">
        <relationship name="effects">
            <destination>{035af29b-1363-4e23-b02b-1c00ba313126}</destination>
            <destination>{436ad8e7-65dc-48e5-aecd-9997e6dd53d3}</destination>
        </relationship>
    </object>
    <object class="MixerBusPanner" id="{48c867fd-18b7-4010-9eff-deca9cc48a3c}"/>
    <object class="MixerBusFader" id="{eeeaf0d2-04a5-46dd-b975-2ad823a516f5}"/>
    <object class="MixerBusEffectChain" id="{7c7c79ce-363f-4f6d-8849-a1a4d633887e}">
        <relationship name="effects">
            <destination>{950e6084-bd1f-407c-a4e2-c8db2682bc73}</destination>
        </relationship>
    </object>
    <object class="MixerBusPanner" id="{729f48dc-30f8-4de9-b212-e4da367e2b7e}"/>
    <object class="MixerBusFader" id="{035af29b-1363-4e23-b02b-1c00ba313126}"/>
    <object class="PluginEffect" id="{436ad8e7-65dc-48e5-aecd-9997e6dd53d3}">
        <relationship name="plugin">
            <destination>{3edae422-88a4-4b54-bf5c-b02a366dbd34}</destination>
        </relationship>
    </object>
    <object class="MixerBusFader" id="{950e6084-bd1f-407c-a4e2-c8db2682bc73}"/>
    <object class="Plugin" id="{3edae422-88a4-4b54-bf5c-b02a366dbd34}">
        <property name="identifier">
            <value>Steam Audio Spatializer</value>
        </property>
        <relationship name="pluginParameters">
            <destination>{2578d835-1b65-40fc-bf02-72c331ce5a93}</destination>
            <destination>{8895a0bb-f5b7-4b72-8517-a8e9a451a62b}</destination>
            <destination>{d1680262-162a-46ce-b7f4-2c080d9a38da}</destination>
            <destination>{6313d4fd-26ee-4812-9ac8-6b4a992c4bc9}</destination>
            <destination>{4bcb7161-3812-421a-89cb-a5c0100d3b59}</destination>
            <destination>{b49d1a61-9407-48fb-a8fe-3b8e5e47e7bc}</destination>
            <destination>{253a338b-ef1d-4419-8979-09fd5313f441}</destination>
            <destination>{e6c51904-a9b8-4afb-983a-9c8f06e6d164}</destination>
            <destination>{bbabf1c7-0494-44d8-b8d9-7e5ae5e3eb7b}</destination>
            <destination>{53873852-0de9-4ee1-9072-d6504ec55bc6}</destination>
            <destination>{072a3c1f-b886-4877-9e72-6986e3a98a4f}</destination>
            <destination>{cbf102d6-749c-4504-9b56-b93c81ac24ac}</destination>
            <destination>{0a221fb2-9486-444d-8d18-d8786a224212}</destination>
            <destination>{d1e96d64-02dd-4f62-ab4c-eb5181b22cee}</destination>
            <destination>{f5d42a4b-5f67-450b-a608-82486ea2b059}</destination>
        </relationship>
    </object>
    <object class="BoolPluginParameter" id="{2578d835-1b65-40fc-bf02-72c331ce5a93}">
        <property name="name">
            <value>DirectBinaural</value>
        </property>
        <property name="value">
            <value>true</value>
        </property>
    </object>
    <object class="IntPluginParameter" id="{8895a0bb-f5b7-4b72-8517-a8e9a451a62b}">
        <property name="name">
            <value>Interpolation</value>
        </property>
        <property name="minimumValue">
            <value>0</value>
        </property>
        <property name="maximumValue">
            <value>1</value>
        </property>
        <property name="value">
            <value>0</value>
        </property>
    </object>
    <object class="BoolPluginParameter" id="{d1680262-162a-46ce-b7f4-2c080d9a38da}">
        <property name="name">
            <value>Distance</value>
        </property>
        <property name="value">
            <value>false</value>
        </property>
    </object>
    <object class="BoolPluginParameter" id="{6313d4fd-26ee-4812-9ac8-6b4a992c4bc9}">
        <property name="name">
            <value>AirAbsorption</value>
        </property>
        <property name="value">
            <value>false</value>
        </property>
    </object>
    <object class="IntPluginParameter" id="{4bcb7161-3812-421a-89cb-a5c0100d3b59}">
        <property name="name">
            <value>OcclusionMode</value>
        </property>
        <property name="minimumValue">
            <value>0</value>
        </property>
        <property name="maximumValue">
            <value>3</value>
        </property>
        <property name="value">
            <value>0</value>
        </property>
    </object>
    <object class="IntPluginParameter" id="{b49d1a61-9407-48fb-a8fe-3b8e5e47e7bc}">
        <property name="name">
            <value>OcclusionMethod</value>
        </property>
        <property name="minimumValue">
            <value>0</value>
        </property>
        <property name="maximumValue">
            <value>1</value>
        </property>
        <property name="value">
            <value>0</value>
        </property>
    </object>
    <object class="FloatPluginParameter" id="{253a338b-ef1d-4419-8979-09fd5313f441}">
        <property name="name">
            <value>SourceRadius</value>
        </property>
        <property name="curve">
            <value>LinearCurveStrategy{(0.000000,0.100000)(1.000000,10.000000)}</value>
        </property>
        <property name="value">
            <value>1</value>
        </property>
    </object>
    <object class="FloatPluginParameter" id="{e6c51904-a9b8-4afb-983a-9c8f06e6d164}">
        <property name="name">
            <value>DirectLevel</value>
        </property>
        <property name="curve">
            <value>LinearCurveStrategy{(0.000000,0.000000)(1.000000,1.000000)}</value>
        </property>
        <property name="value">
            <value>1</value>
        </property>
    </object>
    <object class="BoolPluginParameter" id="{bbabf1c7-0494-44d8-b8d9-7e5ae5e3eb7b}">
        <property name="name">
            <value>Indirect</value>
        </property>
        <property name="value">
            <value>false</value>
        </property>
    </object>
    <object class="BoolPluginParameter" id="{53873852-0de9-4ee1-9072-d6504ec55bc6}">
        <property name="name">
            <value>IndirBinaural</value>
        </property>
        <property name="value">
            <value>false</value>
        </property>
    </object>
    <object class="FloatPluginParameter" id="{072a3c1f-b886-4877-9e72-6986e3a98a4f}">
        <property name="name">
            <value>IndirLevel</value>
        </property>
        <property name="curve">
            <value>LinearCurveStrategy{(0.000000,0.000000)(1.000000,10.000000)}</value>
        </property>
        <property name="value">
            <value>1</value>
        </property>
    </object>
    <object class="IntPluginParameter" id="{cbf102d6-749c-4504-9b56-b93c81ac24ac}">
        <property name="name">
            <value>IndirType</value>
        </property>
        <property name="minimumValue">
            <value>0</value>
        </property>
        <property name="maximumValue">
            <value>1</value>
        </property>
        <property name="value">
            <value>0</value>
        </property>
    </object>
    <object class="BoolPluginParameter" id="{0a221fb2-9486-444d-8d18-d8786a224212}">
        <property name="name">
            <value>StaticListener</value>
        </property>
        <property name="value">
            <value>false</value>
        </property>
    </object>
    <object class="DataPluginParameter" id="{d1e96d64-02dd-4f62-ab4c-eb5181b22cee}">
        <property name="name">
            <value>Name</value>
        </property>
        <property name="dataType">
            <value>0</value>
        </property>
        <property name="value"/>
    </object>
    <object class="DataPluginParameter" id="{f5d42a4b-5f67-450b-a608-82486ea2b059}">
        <property name="name">
            <value>SourcePos</value>
        </property>
        <property name="dataType">
            <value>-2</value>
        </property>
        <property name="value"/>
    </object>
</objects>
