<?xml version="1.0" encoding="UTF-8"?>
<objects serializationModel="Studio.01.10.00">
    <object class="AudioFile" id="{cf7af0da-7c02-4e10-b12f-7e7d27d3c574}">
        <property name="assetPath">
            <value>metal_door_03_open.wav</value>
        </property>
        <property name="frequencyInKHz">
            <value>44.0999985</value>
        </property>
        <property name="channelCount">
            <value>2</value>
        </property>
        <property name="length">
            <value>1.6849659863945579</value>
        </property>
        <relationship name="masterAssetFolder">
            <destination>{f3df849e-9836-45f8-9f26-7b7c0748d2c1}</destination>
        </relationship>
    </object>
</objects>
